dsmr_parser/__init__.py
dsmr_parser/__main__.py
dsmr_parser/exceptions.py
dsmr_parser/obis_references.py
dsmr_parser/objects.py
dsmr_parser/parsers.py
dsmr_parser/profile_generic_specifications.py
dsmr_parser/telegram_specifications.py
dsmr_parser/value_types.py
dsmr_parser/clients/__init__.py
dsmr_parser/clients/filereader.py
dsmr_parser/clients/protocol.py
dsmr_parser/clients/rfxtrx_protocol.py
dsmr_parser/clients/serial_.py
dsmr_parser/clients/settings.py
dsmr_parser/clients/socket_.py
dsmr_parser/clients/telegram_buffer.py
dsmr_parser-1.4.2.dist-info/LICENSE
dsmr_parser-1.4.2.dist-info/METADATA
dsmr_parser-1.4.2.dist-info/WHEEL
dsmr_parser-1.4.2.dist-info/entry_points.txt
dsmr_parser-1.4.2.dist-info/top_level.txt
dsmr_parser-1.4.2.dist-info/RECORD
