Metadata-Version: 2.1
Name: dsmr-parser
Version: 1.4.2
Summary: Library to parse Dutch Smart Meter Requirements (DSMR)
Home-page: https://github.com/ndokter/dsmr_parser
Author: Nigel Dokter and many others
Author-email: mail@nldr.net
License: MIT
License-File: LICENSE
Requires-Dist: pyserial <4,>=3
Requires-Dist: pyserial-asyncio-fast >=0.11
Requires-Dist: pytz
Requires-Dist: Tailer ==0.4.1
Requires-Dist: dlms-cosem ==21.3.2
